datapad/__init__.py
datapad/fields.py
datapad/io.py
datapad/sequence.py
datapad/tests.py
datapad-0.7.6.dist-info/LICENSE
datapad-0.7.6.dist-info/METADATA
datapad-0.7.6.dist-info/WHEEL
datapad-0.7.6.dist-info/top_level.txt
datapad-0.7.6.dist-info/RECORD
