Metadata-Version: 2.1
Name: datapad
Version: 0.7.6
Summary: Datapad is a library of lazy data transformations for sequences; similar to spark and linq
Home-page: https://github.com/huyng/datapad
Author: Huy Nguyen
Author-email: 
License-File: LICENSE
